{
  "aic": "1.2.156.3088.0001.00001.6XYY13.C7IOJG.1.0MYM",
  "active": true,
  "lastModifiedTime": "2026-06-08T15:29:44.425337+08:00",
  "protocolVersion": "02.00",
  "name": "旅行预算评估智能体",
  "description": "旅行预算评估专家。输入行程+POI→Tavily搜索价格→门票/餐饮/住宿/交通/应急五大类费用明细。三档方案(经济/推荐/舒适)，价格范围+置信度+数据来源。拒绝：无行程数据的预算、实时报价承诺。",
  "version": "1.0.0",
  "provider": {
    "organization": "智能体协作实验室",
    "department": "多智能体系统部",
    "url": "https://agents.local",
    "license": "MIT"
  },
  "securitySchemes": {
    "mtls": {
      "type": "mutualTLS",
      "description": "智能体间mTLS双向认证",
      "x-caChallengeBaseUrl": "http://10.126.126.8:8004/acps-atr-v2"
    }
  },
  "endPoints": [
    {
      "url": "http://10.126.126.1:8024/agents/budget_estimator/rpc",
      "transport": "JSONRPC",
      "security": [
        {
          "mtls": []
        }
      ]
    }
  ],
  "capabilities": {
    "streaming": false,
    "notification": false,
    "messageQueue": [
      "rabbitmq:3.*",
      "mqtt:5.*",
      "kafka:>=2.8 <4.0",
      "redis:>=7.0"
    ]
  },
  "defaultInputModes": [
    "text/plain",
    "application/json"
  ],
  "defaultOutputModes": [
    "text/plain",
    "application/json"
  ],
  "skills": [
    {
      "id": "budget-rules.category-breakdown",
      "name": "分类拆解估算法",
      "description": "五大类逐项搜索实时价格，应急储备=总额20%，所有价格标注范围+置信度+来源。",
      "version": "1.0.0",
      "tags": [
        "预算评估",
        "价格搜索",
        "置信度"
      ],
      "examples": [
        "请评估重庆3天2夜的旅行费用预算"
      ],
      "inputModes": [
        "text/plain",
        "application/json"
      ],
      "outputModes": [
        "text/plain",
        "application/json"
      ]
    }
  ]
}
